
	[
		{
			"time" : "2013-04-09 00:58:37",
			"type" : "conversion",
			"user_id" : 23,
			"revenue" : 44.92,
			"id" : 16322
		},
		{
			"time" : "2013-04-09 04:41:44",
			"type" : "conversion",
			"user_id" : 23,
			"revenue" : 37.6,
			"id" : 49060
		},
		{
			"time" : "2013-04-09 04:43:17",
			"type" : "conversion",
			"user_id" : 23,
			"revenue" : 1.54,
			"id" : 72059
		},
		{
			"time" : "2013-04-09 06:29:51",
			"type" : "conversion",
			"user_id" : 23,
			"revenue" : 77.97,
			"id" : 64058
		},
		{
			"time" : "2013-04-09 08:23:43",
			"type" : "conversion",
			"user_id" : 23,
			"revenue" : 81.41,
			"id" : 13775
		},
		{
			"time" : "2013-04-09 08:54:42",
			"type" : "conversion",
			"user_id" : 23,
			"revenue" : 26.53,
			"id" : 30808
		},
		{
			"time" : "2013-04-09 12:27:31",
			"type" : "conversion",
			"user_id" : 23,
			"revenue" : 49.87,
			"id" : 45103
		},
		{
			"time" : "2013-04-09 14:56:27",
			"type" : "conversion",
			"user_id" : 23,
			"revenue" : 5.29,
			"id" : 50223
		},
		{
			"time" : "2013-04-09 15:01:50",
			"type" : "conversion",
			"user_id" : 23,
			"revenue" : 63.69,
			"id" : 16046
		},
		{
			"time" : "2013-04-09 18:05:26",
			"type" : "conversion",
			"user_id" : 23,
			"revenue" : 26.67,
			"id" : 82117
		},
		{
			"time" : "2013-04-09 19:25:50",
			"type" : "conversion",
			"user_id" : 23,
			"revenue" : 9.46,
			"id" : 46032
		},
		{
			"time" : "2013-04-09 20:19:58",
			"type" : "conversion",
			"user_id" : 23,
			"revenue" : 60.25,
			"id" : 39835
		},
		{
			"time" : "2013-04-09 21:40:40",
			"type" : "conversion",
			"user_id" : 23,
			"revenue" : 13.27,
			"id" : 34407
		},
		{
			"time" : "2013-04-09 21:59:12",
			"type" : "conversion",
			"user_id" : 23,
			"revenue" : 55.23,
			"id" : 37440
		},
		{
			"time" : "2013-04-09 22:32:41",
			"type" : "conversion",
			"user_id" : 23,
			"revenue" : 81.55,
			"id" : 46610
		},
		{
			"time" : "2013-04-10 02:19:34",
			"type" : "conversion",
			"user_id" : 23,
			"revenue" : 66.68,
			"id" : 9943
		},
		{
			"time" : "2013-04-10 03:18:59",
			"type" : "conversion",
			"user_id" : 23,
			"revenue" : 66.61,
			"id" : 2220
		},
		{
			"time" : "2013-04-10 04:41:59",
			"type" : "conversion",
			"user_id" : 23,
			"revenue" : 39.78,
			"id" : 39413
		},
		{
			"time" : "2013-04-10 04:44:36",
			"type" : "conversion",
			"user_id" : 23,
			"revenue" : 6.8,
			"id" : 63079
		},
		{
			"time" : "2013-04-10 06:00:55",
			"type" : "conversion",
			"user_id" : 23,
			"revenue" : 53.84,
			"id" : 84069
		},
		{
			"time" : "2013-04-10 06:25:01",
			"type" : "conversion",
			"user_id" : 23,
			"revenue" : 32.53,
			"id" : 74707
		},
		{
			"time" : "2013-04-10 06:46:45",
			"type" : "conversion",
			"user_id" : 23,
			"revenue" : 82.54,
			"id" : 72358
		},
		{
			"time" : "2013-04-10 09:59:28",
			"type" : "conversion",
			"user_id" : 23,
			"revenue" : 93.24,
			"id" : 39735
		},
		{
			"time" : "2013-04-10 10:57:40",
			"type" : "conversion",
			"user_id" : 23,
			"revenue" : 5.51,
			"id" : 99153
		},
		{
			"time" : "2013-04-10 16:36:55",
			"type" : "conversion",
			"user_id" : 23,
			"revenue" : 58.34,
			"id" : 97002
		},
		{
			"time" : "2013-04-10 17:16:54",
			"type" : "conversion",
			"user_id" : 23,
			"revenue" : 91.32,
			"id" : 87976
		},
		{
			"time" : "2013-04-10 17:38:11",
			"type" : "conversion",
			"user_id" : 23,
			"revenue" : 91.83,
			"id" : 68669
		},
		{
			"time" : "2013-04-10 17:40:44",
			"type" : "conversion",
			"user_id" : 23,
			"revenue" : 4.88,
			"id" : 71975
		},
		{
			"time" : "2013-04-10 19:47:43",
			"type" : "conversion",
			"user_id" : 23,
			"revenue" : 60.24,
			"id" : 12645
		},
		{
			"time" : "2013-04-10 19:57:04",
			"type" : "conversion",
			"user_id" : 23,
			"revenue" : 36.68,
			"id" : 65128
		},
		{
			"time" : "2013-04-10 23:24:16",
			"type" : "conversion",
			"user_id" : 23,
			"revenue" : 98.22,
			"id" : 96816
		},
		{
			"time" : "2013-04-10 23:33:08",
			"type" : "conversion",
			"user_id" : 23,
			"revenue" : 75.35,
			"id" : 37721
		},
		{
			"time" : "2013-04-10 23:47:15",
			"type" : "conversion",
			"user_id" : 23,
			"revenue" : 18.73,
			"id" : 78325
		},
		{
			"time" : "2013-04-11 02:07:19",
			"type" : "conversion",
			"user_id" : 23,
			"revenue" : 46.8,
			"id" : 64168
		},
		{
			"time" : "2013-04-11 03:06:57",
			"type" : "conversion",
			"user_id" : 23,
			"revenue" : 0.26,
			"id" : 88861
		},
		{
			"time" : "2013-04-11 09:37:33",
			"type" : "conversion",
			"user_id" : 23,
			"revenue" : 73.31,
			"id" : 63221
		},
		{
			"time" : "2013-04-11 10:25:35",
			"type" : "conversion",
			"user_id" : 23,
			"revenue" : 12.38,
			"id" : 51873
		},
		{
			"time" : "2013-04-11 15:23:47",
			"type" : "conversion",
			"user_id" : 23,
			"revenue" : 17.74,
			"id" : 77235
		},
		{
			"time" : "2013-04-11 21:32:31",
			"type" : "conversion",
			"user_id" : 23,
			"revenue" : 62.49,
			"id" : 65533
		},
		{
			"time" : "2013-04-11 23:43:38",
			"type" : "conversion",
			"user_id" : 23,
			"revenue" : 67.65,
			"id" : 9193
		},
		{
			"time" : "2013-04-12 01:28:38",
			"type" : "conversion",
			"user_id" : 23,
			"revenue" : 26.48,
			"id" : 7077
		},
		{
			"time" : "2013-04-12 07:05:04",
			"type" : "conversion",
			"user_id" : 23,
			"revenue" : 98.76,
			"id" : 22588
		},
		{
			"time" : "2013-04-12 12:36:58",
			"type" : "conversion",
			"user_id" : 23,
			"revenue" : 47.36,
			"id" : 89792
		},
		{
			"time" : "2013-04-12 16:29:48",
			"type" : "conversion",
			"user_id" : 23,
			"revenue" : 18.1,
			"id" : 60130
		},
		{
			"time" : "2013-04-12 18:31:29",
			"type" : "conversion",
			"user_id" : 23,
			"revenue" : 64.85,
			"id" : 45712
		},
		{
			"time" : "2013-04-12 18:56:32",
			"type" : "conversion",
			"user_id" : 23,
			"revenue" : 31.13,
			"id" : 14442
		},
		{
			"time" : "2013-04-13 01:16:41",
			"type" : "conversion",
			"user_id" : 23,
			"revenue" : 72.13,
			"id" : 36327
		},
		{
			"time" : "2013-04-13 02:12:46",
			"type" : "conversion",
			"user_id" : 23,
			"revenue" : 36.88,
			"id" : 70485
		},
		{
			"time" : "2013-04-13 16:38:34",
			"type" : "conversion",
			"user_id" : 23,
			"revenue" : 64.15,
			"id" : 47828
		},
		{
			"time" : "2013-04-13 19:19:15",
			"type" : "conversion",
			"user_id" : 23,
			"revenue" : 26.58,
			"id" : 24926
		},
		{
			"time" : "2013-04-13 19:34:45",
			"type" : "conversion",
			"user_id" : 23,
			"revenue" : 30.94,
			"id" : 17738
		},
		{
			"time" : "2013-04-13 20:07:23",
			"type" : "conversion",
			"user_id" : 23,
			"revenue" : 53.5,
			"id" : 33472
		},
		{
			"time" : "2013-04-13 20:27:01",
			"type" : "conversion",
			"user_id" : 23,
			"revenue" : 28.52,
			"id" : 68854
		},
		{
			"time" : "2013-04-13 22:54:40",
			"type" : "conversion",
			"user_id" : 23,
			"revenue" : 30.95,
			"id" : 61877
		},
		{
			"time" : "2013-04-13 23:14:43",
			"type" : "conversion",
			"user_id" : 23,
			"revenue" : 86.31,
			"id" : 17244
		},
		{
			"time" : "2013-04-14 02:35:14",
			"type" : "conversion",
			"user_id" : 23,
			"revenue" : 49.26,
			"id" : 69121
		},
		{
			"time" : "2013-04-14 07:37:02",
			"type" : "conversion",
			"user_id" : 23,
			"revenue" : 23.72,
			"id" : 67747
		},
		{
			"time" : "2013-04-14 10:26:28",
			"type" : "conversion",
			"user_id" : 23,
			"revenue" : 78.2,
			"id" : 71729
		},
		{
			"time" : "2013-04-14 10:38:14",
			"type" : "conversion",
			"user_id" : 23,
			"revenue" : 3.39,
			"id" : 24987
		},
		{
			"time" : "2013-04-14 11:40:54",
			"type" : "conversion",
			"user_id" : 23,
			"revenue" : 31.29,
			"id" : 90826
		},
		{
			"time" : "2013-04-14 15:09:21",
			"type" : "conversion",
			"user_id" : 23,
			"revenue" : 71.25,
			"id" : 90454
		},
		{
			"time" : "2013-04-14 15:16:51",
			"type" : "conversion",
			"user_id" : 23,
			"revenue" : 52.21,
			"id" : 74049
		},
		{
			"time" : "2013-04-14 17:10:26",
			"type" : "conversion",
			"user_id" : 23,
			"revenue" : 38.39,
			"id" : 17285
		},
		{
			"time" : "2013-04-14 20:09:39",
			"type" : "conversion",
			"user_id" : 23,
			"revenue" : 93.95,
			"id" : 76872
		},
		{
			"time" : "2013-04-14 21:10:16",
			"type" : "conversion",
			"user_id" : 23,
			"revenue" : 71.24,
			"id" : 27616
		},
		{
			"time" : "2013-04-15 00:30:05",
			"type" : "conversion",
			"user_id" : 23,
			"revenue" : 38.87,
			"id" : 7840
		},
		{
			"time" : "2013-04-15 01:24:04",
			"type" : "conversion",
			"user_id" : 23,
			"revenue" : 70.72,
			"id" : 86755
		},
		{
			"time" : "2013-04-15 09:49:03",
			"type" : "conversion",
			"user_id" : 23,
			"revenue" : 95.35,
			"id" : 60095
		},
		{
			"time" : "2013-04-15 10:28:27",
			"type" : "conversion",
			"user_id" : 23,
			"revenue" : 68.75,
			"id" : 8601
		},
		{
			"time" : "2013-04-15 15:44:14",
			"type" : "conversion",
			"user_id" : 23,
			"revenue" : 82.94,
			"id" : 64946
		},
		{
			"time" : "2013-04-15 17:09:08",
			"type" : "conversion",
			"user_id" : 23,
			"revenue" : 7.8,
			"id" : 1517
		},
		{
			"time" : "2013-04-15 18:47:23",
			"type" : "conversion",
			"user_id" : 23,
			"revenue" : 7.65,
			"id" : 30496
		},
		{
			"time" : "2013-04-15 20:03:50",
			"type" : "conversion",
			"user_id" : 23,
			"revenue" : 87.56,
			"id" : 53881
		},
		{
			"time" : "2013-04-15 20:26:11",
			"type" : "conversion",
			"user_id" : 23,
			"revenue" : 40.16,
			"id" : 40242
		},
		{
			"time" : "2013-04-15 23:45:32",
			"type" : "conversion",
			"user_id" : 23,
			"revenue" : 73.97,
			"id" : 62551
		},
		{
			"time" : "2013-04-16 04:39:39",
			"type" : "conversion",
			"user_id" : 23,
			"revenue" : 28.37,
			"id" : 80338
		},
		{
			"time" : "2013-04-16 06:19:01",
			"type" : "conversion",
			"user_id" : 23,
			"revenue" : 45.27,
			"id" : 79284
		},
		{
			"time" : "2013-04-16 12:19:45",
			"type" : "conversion",
			"user_id" : 23,
			"revenue" : 42.64,
			"id" : 20228
		},
		{
			"time" : "2013-04-16 12:38:14",
			"type" : "conversion",
			"user_id" : 23,
			"revenue" : 51.25,
			"id" : 77193
		},
		{
			"time" : "2013-04-16 12:51:16",
			"type" : "conversion",
			"user_id" : 23,
			"revenue" : 12.17,
			"id" : 42550
		},
		{
			"time" : "2013-04-16 12:57:59",
			"type" : "conversion",
			"user_id" : 23,
			"revenue" : 77.73,
			"id" : 87314
		},
		{
			"time" : "2013-04-16 13:45:19",
			"type" : "conversion",
			"user_id" : 23,
			"revenue" : 91.82,
			"id" : 26084
		},
		{
			"time" : "2013-04-16 14:16:01",
			"type" : "conversion",
			"user_id" : 23,
			"revenue" : 73.94,
			"id" : 35885
		},
		{
			"time" : "2013-04-16 14:24:08",
			"type" : "conversion",
			"user_id" : 23,
			"revenue" : 31.29,
			"id" : 30880
		},
		{
			"time" : "2013-04-16 15:02:26",
			"type" : "conversion",
			"user_id" : 23,
			"revenue" : 81.54,
			"id" : 84960
		},
		{
			"time" : "2013-04-16 17:49:56",
			"type" : "conversion",
			"user_id" : 23,
			"revenue" : 32.74,
			"id" : 7213
		},
		{
			"time" : "2013-04-16 19:29:33",
			"type" : "conversion",
			"user_id" : 23,
			"revenue" : 30.14,
			"id" : 27832
		},
		{
			"time" : "2013-04-16 19:51:20",
			"type" : "conversion",
			"user_id" : 23,
			"revenue" : 97.61,
			"id" : 86141
		},
		{
			"time" : "2013-04-16 23:30:41",
			"type" : "conversion",
			"user_id" : 23,
			"revenue" : 24.65,
			"id" : 9231
		},
		{
			"time" : "2013-04-17 02:30:22",
			"type" : "conversion",
			"user_id" : 23,
			"revenue" : 32.24,
			"id" : 69040
		},
		{
			"time" : "2013-04-17 03:24:35",
			"type" : "conversion",
			"user_id" : 23,
			"revenue" : 69.87,
			"id" : 38363
		},
		{
			"time" : "2013-04-17 05:35:07",
			"type" : "conversion",
			"user_id" : 23,
			"revenue" : 84.93,
			"id" : 68427
		},
		{
			"time" : "2013-04-17 10:20:26",
			"type" : "conversion",
			"user_id" : 23,
			"revenue" : 56.48,
			"id" : 47983
		},
		{
			"time" : "2013-04-17 12:59:31",
			"type" : "conversion",
			"user_id" : 23,
			"revenue" : 19.77,
			"id" : 40741
		},
		{
			"time" : "2013-04-17 14:31:57",
			"type" : "conversion",
			"user_id" : 23,
			"revenue" : 7.44,
			"id" : 2141
		},
		{
			"time" : "2013-04-17 16:42:27",
			"type" : "conversion",
			"user_id" : 23,
			"revenue" : 80.39,
			"id" : 59983
		},
		{
			"time" : "2013-04-17 18:07:16",
			"type" : "conversion",
			"user_id" : 23,
			"revenue" : 89.94,
			"id" : 99189
		},
		{
			"time" : "2013-04-17 18:14:55",
			"type" : "conversion",
			"user_id" : 23,
			"revenue" : 12.37,
			"id" : 45257
		},
		{
			"time" : "2013-04-17 21:29:03",
			"type" : "conversion",
			"user_id" : 23,
			"revenue" : 6.71,
			"id" : 47414
		},
		{
			"time" : "2013-04-17 22:43:32",
			"type" : "conversion",
			"user_id" : 23,
			"revenue" : 65.71,
			"id" : 6814
		},
		{
			"time" : "2013-04-18 02:42:07",
			"type" : "conversion",
			"user_id" : 23,
			"revenue" : 77.37,
			"id" : 33215
		},
		{
			"time" : "2013-04-18 05:00:03",
			"type" : "conversion",
			"user_id" : 23,
			"revenue" : 19.22,
			"id" : 94741
		},
		{
			"time" : "2013-04-18 08:35:31",
			"type" : "conversion",
			"user_id" : 23,
			"revenue" : 20.66,
			"id" : 51529
		},
		{
			"time" : "2013-04-18 12:10:54",
			"type" : "conversion",
			"user_id" : 23,
			"revenue" : 22.92,
			"id" : 94931
		},
		{
			"time" : "2013-04-18 12:19:12",
			"type" : "conversion",
			"user_id" : 23,
			"revenue" : 44.23,
			"id" : 75376
		},
		{
			"time" : "2013-04-18 13:57:33",
			"type" : "conversion",
			"user_id" : 23,
			"revenue" : 55.47,
			"id" : 14131
		},
		{
			"time" : "2013-04-18 14:14:06",
			"type" : "conversion",
			"user_id" : 23,
			"revenue" : 32.7,
			"id" : 3944
		},
		{
			"time" : "2013-04-18 14:45:01",
			"type" : "conversion",
			"user_id" : 23,
			"revenue" : 22.33,
			"id" : 96632
		},
		{
			"time" : "2013-04-18 14:58:52",
			"type" : "conversion",
			"user_id" : 23,
			"revenue" : 42.31,
			"id" : 44299
		},
		{
			"time" : "2013-04-18 17:00:34",
			"type" : "conversion",
			"user_id" : 23,
			"revenue" : 38.87,
			"id" : 34602
		},
		{
			"time" : "2013-04-18 17:17:28",
			"type" : "conversion",
			"user_id" : 23,
			"revenue" : 12.84,
			"id" : 61777
		},
		{
			"time" : "2013-04-18 17:25:11",
			"type" : "conversion",
			"user_id" : 23,
			"revenue" : 77.95,
			"id" : 3111
		},
		{
			"time" : "2013-04-18 19:51:18",
			"type" : "conversion",
			"user_id" : 23,
			"revenue" : 37.77,
			"id" : 43774
		},
		{
			"time" : "2013-04-18 20:05:22",
			"type" : "conversion",
			"user_id" : 23,
			"revenue" : 0.11,
			"id" : 2532
		},
		{
			"time" : "2013-04-19 00:12:21",
			"type" : "conversion",
			"user_id" : 23,
			"revenue" : 57.93,
			"id" : 83837
		},
		{
			"time" : "2013-04-19 05:17:47",
			"type" : "conversion",
			"user_id" : 23,
			"revenue" : 22.14,
			"id" : 30033
		},
		{
			"time" : "2013-04-19 06:30:34",
			"type" : "conversion",
			"user_id" : 23,
			"revenue" : 22.64,
			"id" : 79384
		},
		{
			"time" : "2013-04-19 07:37:15",
			"type" : "conversion",
			"user_id" : 23,
			"revenue" : 79.93,
			"id" : 99385
		},
		{
			"time" : "2013-04-19 08:15:10",
			"type" : "conversion",
			"user_id" : 23,
			"revenue" : 68.82,
			"id" : 5835
		},
		{
			"time" : "2013-04-19 15:40:35",
			"type" : "conversion",
			"user_id" : 23,
			"revenue" : 88.4,
			"id" : 41673
		},
		{
			"time" : "2013-04-19 17:43:17",
			"type" : "conversion",
			"user_id" : 23,
			"revenue" : 59.98,
			"id" : 53621
		},
		{
			"time" : "2013-04-19 18:31:52",
			"type" : "conversion",
			"user_id" : 23,
			"revenue" : 6.19,
			"id" : 89117
		},
		{
			"time" : "2013-04-19 19:31:16",
			"type" : "conversion",
			"user_id" : 23,
			"revenue" : 68.48,
			"id" : 6121
		},
		{
			"time" : "2013-04-19 19:37:40",
			"type" : "conversion",
			"user_id" : 23,
			"revenue" : 83.65,
			"id" : 63836
		},
		{
			"time" : "2013-04-19 20:54:25",
			"type" : "conversion",
			"user_id" : 23,
			"revenue" : 9.16,
			"id" : 51340
		},
		{
			"time" : "2013-04-19 21:55:39",
			"type" : "conversion",
			"user_id" : 23,
			"revenue" : 0.74,
			"id" : 75028
		},
		{
			"time" : "2013-04-20 04:12:51",
			"type" : "conversion",
			"user_id" : 23,
			"revenue" : 54.39,
			"id" : 3374
		},
		{
			"time" : "2013-04-20 10:59:37",
			"type" : "conversion",
			"user_id" : 23,
			"revenue" : 12.1,
			"id" : 96172
		},
		{
			"time" : "2013-04-20 13:50:08",
			"type" : "conversion",
			"user_id" : 23,
			"revenue" : 18.7,
			"id" : 60607
		},
		{
			"time" : "2013-04-20 14:25:49",
			"type" : "conversion",
			"user_id" : 23,
			"revenue" : 70.37,
			"id" : 10682
		},
		{
			"time" : "2013-04-20 20:49:28",
			"type" : "conversion",
			"user_id" : 23,
			"revenue" : 41.66,
			"id" : 5003
		},
		{
			"time" : "2013-04-20 21:28:26",
			"type" : "conversion",
			"user_id" : 23,
			"revenue" : 5.66,
			"id" : 23662
		},
		{
			"time" : "2013-04-20 22:06:54",
			"type" : "conversion",
			"user_id" : 23,
			"revenue" : 58.2,
			"id" : 73137
		},
		{
			"time" : "2013-04-21 00:46:28",
			"type" : "conversion",
			"user_id" : 23,
			"revenue" : 7.57,
			"id" : 81250
		},
		{
			"time" : "2013-04-21 02:59:54",
			"type" : "conversion",
			"user_id" : 23,
			"revenue" : 92.16,
			"id" : 68809
		},
		{
			"time" : "2013-04-21 04:15:44",
			"type" : "conversion",
			"user_id" : 23,
			"revenue" : 11.59,
			"id" : 74956
		},
		{
			"time" : "2013-04-21 04:55:55",
			"type" : "conversion",
			"user_id" : 23,
			"revenue" : 47.73,
			"id" : 88330
		},
		{
			"time" : "2013-04-21 05:31:36",
			"type" : "conversion",
			"user_id" : 23,
			"revenue" : 98.16,
			"id" : 67599
		},
		{
			"time" : "2013-04-21 07:20:36",
			"type" : "conversion",
			"user_id" : 23,
			"revenue" : 30.56,
			"id" : 29960
		},
		{
			"time" : "2013-04-21 07:59:07",
			"type" : "conversion",
			"user_id" : 23,
			"revenue" : 38.27,
			"id" : 51972
		},
		{
			"time" : "2013-04-21 16:15:56",
			"type" : "conversion",
			"user_id" : 23,
			"revenue" : 62.78,
			"id" : 99789
		},
		{
			"time" : "2013-04-21 18:50:07",
			"type" : "conversion",
			"user_id" : 23,
			"revenue" : 2.38,
			"id" : 67882
		},
		{
			"time" : "2013-04-21 19:49:34",
			"type" : "conversion",
			"user_id" : 23,
			"revenue" : 69.81,
			"id" : 52149
		},
		{
			"time" : "2013-04-21 19:50:55",
			"type" : "conversion",
			"user_id" : 23,
			"revenue" : 65.32,
			"id" : 51314
		},
		{
			"time" : "2013-04-21 20:45:47",
			"type" : "conversion",
			"user_id" : 23,
			"revenue" : 96.32,
			"id" : 55812
		},
		{
			"time" : "2013-04-21 21:09:19",
			"type" : "conversion",
			"user_id" : 23,
			"revenue" : 64.75,
			"id" : 38905
		},
		{
			"time" : "2013-04-22 07:06:51",
			"type" : "conversion",
			"user_id" : 23,
			"revenue" : 86.21,
			"id" : 89692
		},
		{
			"time" : "2013-04-22 13:38:19",
			"type" : "conversion",
			"user_id" : 23,
			"revenue" : 88.35,
			"id" : 86585
		},
		{
			"time" : "2013-04-22 13:47:28",
			"type" : "conversion",
			"user_id" : 23,
			"revenue" : 16.25,
			"id" : 58658
		},
		{
			"time" : "2013-04-22 15:10:20",
			"type" : "conversion",
			"user_id" : 23,
			"revenue" : 83.94,
			"id" : 3469
		},
		{
			"time" : "2013-04-22 15:42:53",
			"type" : "conversion",
			"user_id" : 23,
			"revenue" : 83.35,
			"id" : 18923
		},
		{
			"time" : "2013-04-22 17:07:37",
			"type" : "conversion",
			"user_id" : 23,
			"revenue" : 40.76,
			"id" : 35429
		},
		{
			"time" : "2013-04-22 18:30:37",
			"type" : "conversion",
			"user_id" : 23,
			"revenue" : 26.16,
			"id" : 62347
		},
		{
			"time" : "2013-04-22 19:37:56",
			"type" : "conversion",
			"user_id" : 23,
			"revenue" : 82.68,
			"id" : 33040
		},
		{
			"time" : "2013-04-23 00:32:56",
			"type" : "conversion",
			"user_id" : 23,
			"revenue" : 13.17,
			"id" : 80872
		},
		{
			"time" : "2013-04-23 01:31:04",
			"type" : "conversion",
			"user_id" : 23,
			"revenue" : 34.86,
			"id" : 36235
		},
		{
			"time" : "2013-04-23 05:08:52",
			"type" : "conversion",
			"user_id" : 23,
			"revenue" : 43.34,
			"id" : 68578
		},
		{
			"time" : "2013-04-23 08:42:46",
			"type" : "conversion",
			"user_id" : 23,
			"revenue" : 50.48,
			"id" : 54265
		},
		{
			"time" : "2013-04-23 21:15:16",
			"type" : "conversion",
			"user_id" : 23,
			"revenue" : 79.62,
			"id" : 14677
		},
		{
			"time" : "2013-04-24 00:13:22",
			"type" : "conversion",
			"user_id" : 23,
			"revenue" : 69.65,
			"id" : 11910
		},
		{
			"time" : "2013-04-24 02:31:25",
			"type" : "conversion",
			"user_id" : 23,
			"revenue" : 12.42,
			"id" : 62776
		},
		{
			"time" : "2013-04-24 03:40:54",
			"type" : "conversion",
			"user_id" : 23,
			"revenue" : 61.22,
			"id" : 27005
		},
		{
			"time" : "2013-04-24 04:33:18",
			"type" : "conversion",
			"user_id" : 23,
			"revenue" : 60.51,
			"id" : 9865
		},
		{
			"time" : "2013-04-24 05:11:37",
			"type" : "conversion",
			"user_id" : 23,
			"revenue" : 95.68,
			"id" : 7409
		},
		{
			"time" : "2013-04-24 07:05:48",
			"type" : "conversion",
			"user_id" : 23,
			"revenue" : 96.11,
			"id" : 18302
		},
		{
			"time" : "2013-04-24 09:01:33",
			"type" : "conversion",
			"user_id" : 23,
			"revenue" : 15.16,
			"id" : 76781
		},
		{
			"time" : "2013-04-24 13:21:58",
			"type" : "conversion",
			"user_id" : 23,
			"revenue" : 3.34,
			"id" : 8174
		},
		{
			"time" : "2013-04-24 16:02:55",
			"type" : "conversion",
			"user_id" : 23,
			"revenue" : 75.79,
			"id" : 33286
		},
		{
			"time" : "2013-04-24 17:12:44",
			"type" : "conversion",
			"user_id" : 23,
			"revenue" : 55.72,
			"id" : 22406
		},
		{
			"time" : "2013-04-24 20:25:37",
			"type" : "conversion",
			"user_id" : 23,
			"revenue" : 98.54,
			"id" : 14404
		},
		{
			"time" : "2013-04-24 21:04:19",
			"type" : "conversion",
			"user_id" : 23,
			"revenue" : 70.23,
			"id" : 50521
		},
		{
			"time" : "2013-04-24 23:21:29",
			"type" : "conversion",
			"user_id" : 23,
			"revenue" : 81.36,
			"id" : 73222
		},
		{
			"time" : "2013-04-24 23:37:36",
			"type" : "conversion",
			"user_id" : 23,
			"revenue" : 30.49,
			"id" : 70154
		},
		{
			"time" : "2013-04-25 01:54:21",
			"type" : "conversion",
			"user_id" : 23,
			"revenue" : 43.59,
			"id" : 42066
		},
		{
			"time" : "2013-04-25 07:25:45",
			"type" : "conversion",
			"user_id" : 23,
			"revenue" : 19.87,
			"id" : 3340
		},
		{
			"time" : "2013-04-25 08:04:03",
			"type" : "conversion",
			"user_id" : 23,
			"revenue" : 15.35,
			"id" : 65271
		},
		{
			"time" : "2013-04-25 08:20:52",
			"type" : "conversion",
			"user_id" : 23,
			"revenue" : 60.32,
			"id" : 94755
		},
		{
			"time" : "2013-04-25 10:59:08",
			"type" : "conversion",
			"user_id" : 23,
			"revenue" : 56.41,
			"id" : 33640
		},
		{
			"time" : "2013-04-25 19:27:58",
			"type" : "conversion",
			"user_id" : 23,
			"revenue" : 59.68,
			"id" : 65914
		},
		{
			"time" : "2013-04-25 20:57:48",
			"type" : "conversion",
			"user_id" : 23,
			"revenue" : 81.39,
			"id" : 10674
		},
		{
			"time" : "2013-04-25 21:14:26",
			"type" : "conversion",
			"user_id" : 23,
			"revenue" : 98.82,
			"id" : 47781
		},
		{
			"time" : "2013-04-25 21:26:23",
			"type" : "conversion",
			"user_id" : 23,
			"revenue" : 35.86,
			"id" : 27676
		},
		{
			"time" : "2013-04-26 00:48:58",
			"type" : "conversion",
			"user_id" : 23,
			"revenue" : 11.68,
			"id" : 43431
		},
		{
			"time" : "2013-04-26 05:40:42",
			"type" : "conversion",
			"user_id" : 23,
			"revenue" : 65.33,
			"id" : 92161
		},
		{
			"time" : "2013-04-26 08:59:28",
			"type" : "conversion",
			"user_id" : 23,
			"revenue" : 20.22,
			"id" : 13218
		},
		{
			"time" : "2013-04-26 09:30:20",
			"type" : "conversion",
			"user_id" : 23,
			"revenue" : 13.92,
			"id" : 89536
		},
		{
			"time" : "2013-04-26 09:36:40",
			"type" : "conversion",
			"user_id" : 23,
			"revenue" : 67.82,
			"id" : 20368
		},
		{
			"time" : "2013-04-26 09:37:00",
			"type" : "conversion",
			"user_id" : 23,
			"revenue" : 49.62,
			"id" : 27183
		},
		{
			"time" : "2013-04-26 23:59:32",
			"type" : "conversion",
			"user_id" : 23,
			"revenue" : 18.41,
			"id" : 32766
		},
		{
			"time" : "2013-04-27 00:49:16",
			"type" : "conversion",
			"user_id" : 23,
			"revenue" : 70.39,
			"id" : 18778
		},
		{
			"time" : "2013-04-27 02:24:00",
			"type" : "conversion",
			"user_id" : 23,
			"revenue" : 63.79,
			"id" : 90670
		},
		{
			"time" : "2013-04-27 03:10:38",
			"type" : "conversion",
			"user_id" : 23,
			"revenue" : 8.67,
			"id" : 37430
		},
		{
			"time" : "2013-04-27 04:17:17",
			"type" : "conversion",
			"user_id" : 23,
			"revenue" : 3.46,
			"id" : 22864
		},
		{
			"time" : "2013-04-27 05:51:38",
			"type" : "conversion",
			"user_id" : 23,
			"revenue" : 42.62,
			"id" : 12548
		},
		{
			"time" : "2013-04-27 07:37:37",
			"type" : "conversion",
			"user_id" : 23,
			"revenue" : 9.97,
			"id" : 37651
		},
		{
			"time" : "2013-04-27 11:04:08",
			"type" : "conversion",
			"user_id" : 23,
			"revenue" : 16.69,
			"id" : 44688
		},
		{
			"time" : "2013-04-27 12:21:32",
			"type" : "conversion",
			"user_id" : 23,
			"revenue" : 11.27,
			"id" : 19932
		},
		{
			"time" : "2013-04-27 12:22:08",
			"type" : "conversion",
			"user_id" : 23,
			"revenue" : 81.36,
			"id" : 33259
		},
		{
			"time" : "2013-04-27 20:17:31",
			"type" : "conversion",
			"user_id" : 23,
			"revenue" : 31.14,
			"id" : 90013
		},
		{
			"time" : "2013-04-27 20:33:42",
			"type" : "conversion",
			"user_id" : 23,
			"revenue" : 53.68,
			"id" : 93247
		},
		{
			"time" : "2013-04-27 21:03:43",
			"type" : "conversion",
			"user_id" : 23,
			"revenue" : 27.94,
			"id" : 71773
		},
		{
			"time" : "2013-04-27 21:27:44",
			"type" : "conversion",
			"user_id" : 23,
			"revenue" : 68.49,
			"id" : 17376
		},
		{
			"time" : "2013-04-28 06:09:47",
			"type" : "conversion",
			"user_id" : 23,
			"revenue" : 95.79,
			"id" : 86774
		},
		{
			"time" : "2013-04-28 09:05:33",
			"type" : "conversion",
			"user_id" : 23,
			"revenue" : 34.65,
			"id" : 34482
		},
		{
			"time" : "2013-04-28 09:50:56",
			"type" : "conversion",
			"user_id" : 23,
			"revenue" : 97.84,
			"id" : 52655
		},
		{
			"time" : "2013-04-28 10:46:42",
			"type" : "conversion",
			"user_id" : 23,
			"revenue" : 67.14,
			"id" : 98142
		},
		{
			"time" : "2013-04-28 11:06:59",
			"type" : "conversion",
			"user_id" : 23,
			"revenue" : 79.67,
			"id" : 40160
		},
		{
			"time" : "2013-04-28 15:12:14",
			"type" : "conversion",
			"user_id" : 23,
			"revenue" : 84.85,
			"id" : 29756
		},
		{
			"time" : "2013-04-28 16:15:08",
			"type" : "conversion",
			"user_id" : 23,
			"revenue" : 93.78,
			"id" : 40843
		},
		{
			"time" : "2013-04-28 16:16:17",
			"type" : "conversion",
			"user_id" : 23,
			"revenue" : 86.66,
			"id" : 79404
		},
		{
			"time" : "2013-04-28 16:51:33",
			"type" : "conversion",
			"user_id" : 23,
			"revenue" : 86.12,
			"id" : 14761
		},
		{
			"time" : "2013-04-28 17:25:38",
			"type" : "conversion",
			"user_id" : 23,
			"revenue" : 46.65,
			"id" : 64645
		},
		{
			"time" : "2013-04-28 18:23:56",
			"type" : "conversion",
			"user_id" : 23,
			"revenue" : 27.17,
			"id" : 12909
		},
		{
			"time" : "2013-04-28 22:03:20",
			"type" : "conversion",
			"user_id" : 23,
			"revenue" : 30.43,
			"id" : 92269
		},
		{
			"time" : "2013-04-28 22:53:44",
			"type" : "conversion",
			"user_id" : 23,
			"revenue" : 58.84,
			"id" : 17409
		},
		{
			"time" : "2013-04-29 00:12:21",
			"type" : "conversion",
			"user_id" : 23,
			"revenue" : 47.89,
			"id" : 7628
		},
		{
			"time" : "2013-04-29 01:58:56",
			"type" : "conversion",
			"user_id" : 23,
			"revenue" : 79.7,
			"id" : 77462
		},
		{
			"time" : "2013-04-29 03:13:56",
			"type" : "conversion",
			"user_id" : 23,
			"revenue" : 57.75,
			"id" : 40177
		},
		{
			"time" : "2013-04-29 03:55:29",
			"type" : "conversion",
			"user_id" : 23,
			"revenue" : 2.92,
			"id" : 36855
		},
		{
			"time" : "2013-04-29 05:58:22",
			"type" : "conversion",
			"user_id" : 23,
			"revenue" : 94.65,
			"id" : 59476
		},
		{
			"time" : "2013-04-29 08:59:28",
			"type" : "conversion",
			"user_id" : 23,
			"revenue" : 86.62,
			"id" : 38149
		},
		{
			"time" : "2013-04-29 09:22:54",
			"type" : "conversion",
			"user_id" : 23,
			"revenue" : 66.27,
			"id" : 41415
		},
		{
			"time" : "2013-04-29 10:11:35",
			"type" : "conversion",
			"user_id" : 23,
			"revenue" : 30.38,
			"id" : 82724
		},
		{
			"time" : "2013-04-29 22:55:13",
			"type" : "conversion",
			"user_id" : 23,
			"revenue" : 90.47,
			"id" : 33317
		},
		{
			"time" : "2013-04-30 03:12:20",
			"type" : "conversion",
			"user_id" : 23,
			"revenue" : 15.7,
			"id" : 25579
		},
		{
			"time" : "2013-04-30 03:32:36",
			"type" : "conversion",
			"user_id" : 23,
			"revenue" : 43.48,
			"id" : 84136
		},
		{
			"time" : "2013-04-30 10:30:15",
			"type" : "conversion",
			"user_id" : 23,
			"revenue" : 41.86,
			"id" : 67192
		},
		{
			"time" : "2013-04-30 12:53:02",
			"type" : "conversion",
			"user_id" : 23,
			"revenue" : 70.35,
			"id" : 48431
		},
		{
			"time" : "2013-04-30 15:29:10",
			"type" : "conversion",
			"user_id" : 23,
			"revenue" : 15.43,
			"id" : 35030
		},
		{
			"time" : "2013-04-30 17:06:37",
			"type" : "conversion",
			"user_id" : 23,
			"revenue" : 88.17,
			"id" : 63728
		},
		{
			"time" : "2013-04-30 19:08:58",
			"type" : "conversion",
			"user_id" : 23,
			"revenue" : 83.89,
			"id" : 41672
		},
		{
			"time" : "2013-04-30 20:03:46",
			"type" : "conversion",
			"user_id" : 23,
			"revenue" : 97.9,
			"id" : 61254
		},
		{
			"time" : "2013-04-30 22:12:31",
			"type" : "conversion",
			"user_id" : 23,
			"revenue" : 33.16,
			"id" : 55448
		},
		{
			"time" : "2013-05-01 00:30:19",
			"type" : "conversion",
			"user_id" : 23,
			"revenue" : 71.37,
			"id" : 75121
		},
		{
			"time" : "2013-05-01 01:09:39",
			"type" : "conversion",
			"user_id" : 23,
			"revenue" : 43.66,
			"id" : 84407
		},
		{
			"time" : "2013-05-01 06:56:40",
			"type" : "conversion",
			"user_id" : 23,
			"revenue" : 76.75,
			"id" : 44507
		},
		{
			"time" : "2013-05-01 08:12:18",
			"type" : "conversion",
			"user_id" : 23,
			"revenue" : 28.96,
			"id" : 30600
		},
		{
			"time" : "2013-05-01 14:39:13",
			"type" : "conversion",
			"user_id" : 23,
			"revenue" : 68.23,
			"id" : 91584
		},
		{
			"time" : "2013-05-01 18:42:11",
			"type" : "conversion",
			"user_id" : 23,
			"revenue" : 76.17,
			"id" : 54217
		},
		{
			"time" : "2013-05-01 20:33:32",
			"type" : "conversion",
			"user_id" : 23,
			"revenue" : 12.38,
			"id" : 70398
		},
		{
			"time" : "2013-05-01 21:53:40",
			"type" : "conversion",
			"user_id" : 23,
			"revenue" : 3.29,
			"id" : 7016
		},
		{
			"time" : "2013-05-02 00:11:22",
			"type" : "conversion",
			"user_id" : 23,
			"revenue" : 45.51,
			"id" : 53867
		},
		{
			"time" : "2013-05-02 04:50:45",
			"type" : "conversion",
			"user_id" : 23,
			"revenue" : 6.34,
			"id" : 45260
		},
		{
			"time" : "2013-05-02 06:43:22",
			"type" : "conversion",
			"user_id" : 23,
			"revenue" : 37.94,
			"id" : 61662
		},
		{
			"time" : "2013-05-02 11:43:40",
			"type" : "conversion",
			"user_id" : 23,
			"revenue" : 26.24,
			"id" : 29476
		},
		{
			"time" : "2013-05-02 12:14:14",
			"type" : "conversion",
			"user_id" : 23,
			"revenue" : 31.29,
			"id" : 79644
		},
		{
			"time" : "2013-05-02 12:38:19",
			"type" : "conversion",
			"user_id" : 23,
			"revenue" : 13.94,
			"id" : 24633
		},
		{
			"time" : "2013-05-02 14:32:21",
			"type" : "conversion",
			"user_id" : 23,
			"revenue" : 31.77,
			"id" : 6790
		},
		{
			"time" : "2013-05-02 16:45:42",
			"type" : "conversion",
			"user_id" : 23,
			"revenue" : 94.97,
			"id" : 9739
		},
		{
			"time" : "2013-05-02 16:51:03",
			"type" : "conversion",
			"user_id" : 23,
			"revenue" : 37.63,
			"id" : 46492
		},
		{
			"time" : "2013-05-02 20:40:47",
			"type" : "conversion",
			"user_id" : 23,
			"revenue" : 80.59,
			"id" : 62673
		},
		{
			"time" : "2013-05-02 22:43:09",
			"type" : "conversion",
			"user_id" : 23,
			"revenue" : 27.2,
			"id" : 93314
		},
		{
			"time" : "2013-05-02 22:47:33",
			"type" : "conversion",
			"user_id" : 23,
			"revenue" : 47.57,
			"id" : 91500
		},
		{
			"time" : "2013-05-03 09:36:58",
			"type" : "conversion",
			"user_id" : 23,
			"revenue" : 73.89,
			"id" : 8408
		},
		{
			"time" : "2013-05-03 12:10:13",
			"type" : "conversion",
			"user_id" : 23,
			"revenue" : 74.95,
			"id" : 88795
		},
		{
			"time" : "2013-05-03 12:27:11",
			"type" : "conversion",
			"user_id" : 23,
			"revenue" : 31.66,
			"id" : 63255
		},
		{
			"time" : "2013-05-03 12:40:49",
			"type" : "conversion",
			"user_id" : 23,
			"revenue" : 15.3,
			"id" : 54123
		},
		{
			"time" : "2013-05-03 13:05:09",
			"type" : "conversion",
			"user_id" : 23,
			"revenue" : 91.58,
			"id" : 21795
		},
		{
			"time" : "2013-05-03 17:40:22",
			"type" : "conversion",
			"user_id" : 23,
			"revenue" : 86.96,
			"id" : 70137
		},
		{
			"time" : "2013-05-03 20:20:15",
			"type" : "conversion",
			"user_id" : 23,
			"revenue" : 98.41,
			"id" : 96175
		},
		{
			"time" : "2013-05-03 21:14:58",
			"type" : "conversion",
			"user_id" : 23,
			"revenue" : 40.59,
			"id" : 30775
		},
		{
			"time" : "2013-05-03 22:01:18",
			"type" : "conversion",
			"user_id" : 23,
			"revenue" : 11.67,
			"id" : 78209
		},
		{
			"time" : "2013-05-03 22:18:06",
			"type" : "conversion",
			"user_id" : 23,
			"revenue" : 23.95,
			"id" : 347
		},
		{
			"time" : "2013-05-03 23:51:13",
			"type" : "conversion",
			"user_id" : 23,
			"revenue" : 41.59,
			"id" : 58664
		},
		{
			"time" : "2013-05-04 01:57:31",
			"type" : "conversion",
			"user_id" : 23,
			"revenue" : 18.23,
			"id" : 88523
		},
		{
			"time" : "2013-05-04 03:24:02",
			"type" : "conversion",
			"user_id" : 23,
			"revenue" : 26.89,
			"id" : 304
		},
		{
			"time" : "2013-05-04 05:39:02",
			"type" : "conversion",
			"user_id" : 23,
			"revenue" : 78.26,
			"id" : 13154
		},
		{
			"time" : "2013-05-04 07:13:57",
			"type" : "conversion",
			"user_id" : 23,
			"revenue" : 94.92,
			"id" : 81024
		},
		{
			"time" : "2013-05-04 08:01:00",
			"type" : "conversion",
			"user_id" : 23,
			"revenue" : 28.62,
			"id" : 37159
		},
		{
			"time" : "2013-05-04 09:09:23",
			"type" : "conversion",
			"user_id" : 23,
			"revenue" : 52.53,
			"id" : 47891
		},
		{
			"time" : "2013-05-04 11:41:22",
			"type" : "conversion",
			"user_id" : 23,
			"revenue" : 26.59,
			"id" : 46596
		},
		{
			"time" : "2013-05-04 14:17:40",
			"type" : "conversion",
			"user_id" : 23,
			"revenue" : 55.49,
			"id" : 28488
		},
		{
			"time" : "2013-05-04 14:18:16",
			"type" : "conversion",
			"user_id" : 23,
			"revenue" : 69.89,
			"id" : 78738
		},
		{
			"time" : "2013-05-04 14:52:36",
			"type" : "conversion",
			"user_id" : 23,
			"revenue" : 74.25,
			"id" : 61987
		},
		{
			"time" : "2013-05-04 15:54:59",
			"type" : "conversion",
			"user_id" : 23,
			"revenue" : 58.98,
			"id" : 70241
		},
		{
			"time" : "2013-05-04 16:42:05",
			"type" : "conversion",
			"user_id" : 23,
			"revenue" : 13.71,
			"id" : 308
		},
		{
			"time" : "2013-05-04 18:36:31",
			"type" : "conversion",
			"user_id" : 23,
			"revenue" : 99.71,
			"id" : 87438
		},
		{
			"time" : "2013-05-04 20:47:33",
			"type" : "conversion",
			"user_id" : 23,
			"revenue" : 81.78,
			"id" : 22052
		},
		{
			"time" : "2013-05-04 23:41:59",
			"type" : "conversion",
			"user_id" : 23,
			"revenue" : 97.49,
			"id" : 2835
		},
		{
			"time" : "2013-05-05 00:10:08",
			"type" : "conversion",
			"user_id" : 23,
			"revenue" : 80.53,
			"id" : 48802
		},
		{
			"time" : "2013-05-05 07:01:33",
			"type" : "conversion",
			"user_id" : 23,
			"revenue" : 43.28,
			"id" : 39570
		},
		{
			"time" : "2013-05-05 08:33:09",
			"type" : "conversion",
			"user_id" : 23,
			"revenue" : 4.78,
			"id" : 78304
		},
		{
			"time" : "2013-05-05 08:40:27",
			"type" : "conversion",
			"user_id" : 23,
			"revenue" : 17.58,
			"id" : 95978
		},
		{
			"time" : "2013-05-05 09:35:53",
			"type" : "conversion",
			"user_id" : 23,
			"revenue" : 90.41,
			"id" : 21586
		},
		{
			"time" : "2013-05-05 10:20:08",
			"type" : "conversion",
			"user_id" : 23,
			"revenue" : 37.81,
			"id" : 93767
		},
		{
			"time" : "2013-05-05 10:21:01",
			"type" : "conversion",
			"user_id" : 23,
			"revenue" : 54.63,
			"id" : 59791
		},
		{
			"time" : "2013-05-05 10:38:20",
			"type" : "conversion",
			"user_id" : 23,
			"revenue" : 64.65,
			"id" : 28510
		},
		{
			"time" : "2013-05-05 11:21:25",
			"type" : "conversion",
			"user_id" : 23,
			"revenue" : 36.36,
			"id" : 50692
		},
		{
			"time" : "2013-05-05 13:32:17",
			"type" : "conversion",
			"user_id" : 23,
			"revenue" : 46.67,
			"id" : 11938
		},
		{
			"time" : "2013-05-05 14:02:16",
			"type" : "conversion",
			"user_id" : 23,
			"revenue" : 97.51,
			"id" : 82656
		},
		{
			"time" : "2013-05-05 18:01:29",
			"type" : "conversion",
			"user_id" : 23,
			"revenue" : 63.64,
			"id" : 65696
		},
		{
			"time" : "2013-05-05 18:54:33",
			"type" : "conversion",
			"user_id" : 23,
			"revenue" : 6.71,
			"id" : 68955
		},
		{
			"time" : "2013-05-05 19:05:05",
			"type" : "conversion",
			"user_id" : 23,
			"revenue" : 33.95,
			"id" : 66008
		},
		{
			"time" : "2013-05-05 19:49:02",
			"type" : "conversion",
			"user_id" : 23,
			"revenue" : 77.51,
			"id" : 85944
		},
		{
			"time" : "2013-05-05 21:45:19",
			"type" : "conversion",
			"user_id" : 23,
			"revenue" : 66.89,
			"id" : 81588
		},
		{
			"time" : "2013-05-05 22:53:01",
			"type" : "conversion",
			"user_id" : 23,
			"revenue" : 79.87,
			"id" : 17334
		},
		{
			"time" : "2013-05-06 07:02:23",
			"type" : "conversion",
			"user_id" : 23,
			"revenue" : 3.3,
			"id" : 49906
		},
		{
			"time" : "2013-05-06 11:40:26",
			"type" : "conversion",
			"user_id" : 23,
			"revenue" : 99.66,
			"id" : 8247
		},
		{
			"time" : "2013-05-06 12:02:24",
			"type" : "conversion",
			"user_id" : 23,
			"revenue" : 69.17,
			"id" : 95034
		},
		{
			"time" : "2013-05-06 15:20:10",
			"type" : "conversion",
			"user_id" : 23,
			"revenue" : 7.53,
			"id" : 89604
		},
		{
			"time" : "2013-05-06 15:22:04",
			"type" : "conversion",
			"user_id" : 23,
			"revenue" : 66.62,
			"id" : 46820
		},
		{
			"time" : "2013-05-06 15:54:37",
			"type" : "conversion",
			"user_id" : 23,
			"revenue" : 91.36,
			"id" : 25587
		},
		{
			"time" : "2013-05-06 19:35:21",
			"type" : "conversion",
			"user_id" : 23,
			"revenue" : 76.67,
			"id" : 26960
		},
		{
			"time" : "2013-05-06 20:01:38",
			"type" : "conversion",
			"user_id" : 23,
			"revenue" : 39.97,
			"id" : 51776
		},
		{
			"time" : "2013-05-06 21:16:49",
			"type" : "conversion",
			"user_id" : 23,
			"revenue" : 23.65,
			"id" : 66595
		},
		{
			"time" : "2013-05-07 02:29:48",
			"type" : "conversion",
			"user_id" : 23,
			"revenue" : 51.41,
			"id" : 9269
		},
		{
			"time" : "2013-05-07 02:47:38",
			"type" : "conversion",
			"user_id" : 23,
			"revenue" : 18.37,
			"id" : 3571
		},
		{
			"time" : "2013-05-07 05:42:53",
			"type" : "conversion",
			"user_id" : 23,
			"revenue" : 1.26,
			"id" : 60172
		},
		{
			"time" : "2013-05-07 06:12:29",
			"type" : "conversion",
			"user_id" : 23,
			"revenue" : 90.17,
			"id" : 54576
		},
		{
			"time" : "2013-05-07 12:29:47",
			"type" : "conversion",
			"user_id" : 23,
			"revenue" : 13.92,
			"id" : 59420
		},
		{
			"time" : "2013-05-07 15:17:50",
			"type" : "conversion",
			"user_id" : 23,
			"revenue" : 83.68,
			"id" : 24618
		},
		{
			"time" : "2013-05-07 15:33:08",
			"type" : "conversion",
			"user_id" : 23,
			"revenue" : 34.53,
			"id" : 29657
		},
		{
			"time" : "2013-05-07 17:12:28",
			"type" : "conversion",
			"user_id" : 23,
			"revenue" : 58.58,
			"id" : 40172
		},
		{
			"time" : "2013-05-07 20:39:38",
			"type" : "conversion",
			"user_id" : 23,
			"revenue" : 23.23,
			"id" : 43909
		},
		{
			"time" : "2013-05-08 03:03:34",
			"type" : "conversion",
			"user_id" : 23,
			"revenue" : 90.75,
			"id" : 89594
		},
		{
			"time" : "2013-05-08 04:51:39",
			"type" : "conversion",
			"user_id" : 23,
			"revenue" : 98.39,
			"id" : 53574
		},
		{
			"time" : "2013-05-08 06:41:32",
			"type" : "conversion",
			"user_id" : 23,
			"revenue" : 27.3,
			"id" : 53774
		},
		{
			"time" : "2013-05-08 10:38:17",
			"type" : "conversion",
			"user_id" : 23,
			"revenue" : 64.2,
			"id" : 28183
		},
		{
			"time" : "2013-05-08 11:39:10",
			"type" : "conversion",
			"user_id" : 23,
			"revenue" : 49.76,
			"id" : 61738
		},
		{
			"time" : "2013-05-08 23:38:24",
			"type" : "conversion",
			"user_id" : 23,
			"revenue" : 99.18,
			"id" : 15442
		}
	]